server_litellm/__init__.py
server_litellm/__main__.py
server_litellm/server.py
iflow_mcp_itsdarianngo_mcp_server_litellm-0.1.0.dist-info/METADATA
iflow_mcp_itsdarianngo_mcp_server_litellm-0.1.0.dist-info/WHEEL
iflow_mcp_itsdarianngo_mcp_server_litellm-0.1.0.dist-info/entry_points.txt
iflow_mcp_itsdarianngo_mcp_server_litellm-0.1.0.dist-info/RECORD
